{
  "id": "a5391237-d355-4480-b19d-717e61f6de8f",
  "prevId": "ca151bf2-c818-4d95-af98-462a5d753fb7",
  "version": "7",
  "dialect": "postgresql",
  "tables": {
    "public.household": {
      "name": "household",
      "schema": "",
      "columns": {
        "id": {
          "name": "id",
          "type": "uuid",
          "primaryKey": true,
          "notNull": true,
          "default": "gen_random_uuid()"
        },
        "singleton": {
          "name": "singleton",
          "type": "boolean",
          "primaryKey": false,
          "notNull": true,
          "default": true
        },
        "setup_complete": {
          "name": "setup_complete",
          "type": "boolean",
          "primaryKey": false,
          "notNull": true,
          "default": false
        },
        "version": {
          "name": "version",
          "type": "integer",
          "primaryKey": false,
          "notNull": true,
          "default": 0
        },
        "created_at": {
          "name": "created_at",
          "type": "timestamp with time zone",
          "primaryKey": false,
          "notNull": true,
          "default": "now()"
        }
      },
      "indexes": {},
      "foreignKeys": {},
      "compositePrimaryKeys": {},
      "uniqueConstraints": {
        "household_singleton_unique": {
          "name": "household_singleton_unique",
          "nullsNotDistinct": false,
          "columns": [
            "singleton"
          ]
        }
      },
      "policies": {},
      "checkConstraints": {},
      "isRLSEnabled": false
    },
    "public.ingredient": {
      "name": "ingredient",
      "schema": "",
      "columns": {
        "id": {
          "name": "id",
          "type": "uuid",
          "primaryKey": true,
          "notNull": true,
          "default": "gen_random_uuid()"
        },
        "canonical_name": {
          "name": "canonical_name",
          "type": "text",
          "primaryKey": false,
          "notNull": true
        },
        "synonyms": {
          "name": "synonyms",
          "type": "text[]",
          "primaryKey": false,
          "notNull": false
        },
        "category": {
          "name": "category",
          "type": "text",
          "primaryKey": false,
          "notNull": false
        },
        "created_at": {
          "name": "created_at",
          "type": "timestamp with time zone",
          "primaryKey": false,
          "notNull": true,
          "default": "now()"
        }
      },
      "indexes": {},
      "foreignKeys": {},
      "compositePrimaryKeys": {},
      "uniqueConstraints": {
        "ingredient_canonical_name_unique": {
          "name": "ingredient_canonical_name_unique",
          "nullsNotDistinct": false,
          "columns": [
            "canonical_name"
          ]
        }
      },
      "policies": {},
      "checkConstraints": {},
      "isRLSEnabled": false
    },
    "public.ingredient_allergen": {
      "name": "ingredient_allergen",
      "schema": "",
      "columns": {
        "id": {
          "name": "id",
          "type": "uuid",
          "primaryKey": true,
          "notNull": true,
          "default": "gen_random_uuid()"
        },
        "ingredient_id": {
          "name": "ingredient_id",
          "type": "uuid",
          "primaryKey": false,
          "notNull": true
        },
        "allergen": {
          "name": "allergen",
          "type": "allergen",
          "typeSchema": "public",
          "primaryKey": false,
          "notNull": true
        }
      },
      "indexes": {},
      "foreignKeys": {
        "ingredient_allergen_ingredient_id_ingredient_id_fk": {
          "name": "ingredient_allergen_ingredient_id_ingredient_id_fk",
          "tableFrom": "ingredient_allergen",
          "tableTo": "ingredient",
          "columnsFrom": [
            "ingredient_id"
          ],
          "columnsTo": [
            "id"
          ],
          "onDelete": "cascade",
          "onUpdate": "no action"
        }
      },
      "compositePrimaryKeys": {},
      "uniqueConstraints": {},
      "policies": {},
      "checkConstraints": {},
      "isRLSEnabled": false
    },
    "public.member": {
      "name": "member",
      "schema": "",
      "columns": {
        "id": {
          "name": "id",
          "type": "uuid",
          "primaryKey": true,
          "notNull": true,
          "default": "gen_random_uuid()"
        },
        "household_id": {
          "name": "household_id",
          "type": "uuid",
          "primaryKey": false,
          "notNull": true
        },
        "name": {
          "name": "name",
          "type": "text",
          "primaryKey": false,
          "notNull": true
        },
        "birthdate": {
          "name": "birthdate",
          "type": "date",
          "primaryKey": false,
          "notNull": false
        },
        "is_eater": {
          "name": "is_eater",
          "type": "boolean",
          "primaryKey": false,
          "notNull": true,
          "default": true
        },
        "created_at": {
          "name": "created_at",
          "type": "timestamp with time zone",
          "primaryKey": false,
          "notNull": true,
          "default": "now()"
        }
      },
      "indexes": {},
      "foreignKeys": {
        "member_household_id_household_id_fk": {
          "name": "member_household_id_household_id_fk",
          "tableFrom": "member",
          "tableTo": "household",
          "columnsFrom": [
            "household_id"
          ],
          "columnsTo": [
            "id"
          ],
          "onDelete": "cascade",
          "onUpdate": "no action"
        }
      },
      "compositePrimaryKeys": {},
      "uniqueConstraints": {},
      "policies": {},
      "checkConstraints": {},
      "isRLSEnabled": false
    },
    "public.recipe": {
      "name": "recipe",
      "schema": "",
      "columns": {
        "id": {
          "name": "id",
          "type": "uuid",
          "primaryKey": true,
          "notNull": true,
          "default": "gen_random_uuid()"
        },
        "household_id": {
          "name": "household_id",
          "type": "uuid",
          "primaryKey": false,
          "notNull": true
        },
        "title": {
          "name": "title",
          "type": "text",
          "primaryKey": false,
          "notNull": true
        },
        "prep_minutes": {
          "name": "prep_minutes",
          "type": "integer",
          "primaryKey": false,
          "notNull": false
        },
        "cook_minutes": {
          "name": "cook_minutes",
          "type": "integer",
          "primaryKey": false,
          "notNull": false
        },
        "effort_tier": {
          "name": "effort_tier",
          "type": "effort_tier",
          "typeSchema": "public",
          "primaryKey": false,
          "notNull": false
        },
        "seasons": {
          "name": "seasons",
          "type": "text[]",
          "primaryKey": false,
          "notNull": false
        },
        "deconstructable": {
          "name": "deconstructable",
          "type": "boolean",
          "primaryKey": false,
          "notNull": true,
          "default": false
        },
        "kid_adaptable": {
          "name": "kid_adaptable",
          "type": "boolean",
          "primaryKey": false,
          "notNull": true,
          "default": false
        },
        "human_confirmed": {
          "name": "human_confirmed",
          "type": "boolean",
          "primaryKey": false,
          "notNull": true,
          "default": false
        },
        "deleted_at": {
          "name": "deleted_at",
          "type": "timestamp with time zone",
          "primaryKey": false,
          "notNull": false
        },
        "version": {
          "name": "version",
          "type": "integer",
          "primaryKey": false,
          "notNull": true,
          "default": 0
        },
        "created_at": {
          "name": "created_at",
          "type": "timestamp with time zone",
          "primaryKey": false,
          "notNull": true,
          "default": "now()"
        }
      },
      "indexes": {},
      "foreignKeys": {
        "recipe_household_id_household_id_fk": {
          "name": "recipe_household_id_household_id_fk",
          "tableFrom": "recipe",
          "tableTo": "household",
          "columnsFrom": [
            "household_id"
          ],
          "columnsTo": [
            "id"
          ],
          "onDelete": "cascade",
          "onUpdate": "no action"
        }
      },
      "compositePrimaryKeys": {},
      "uniqueConstraints": {},
      "policies": {},
      "checkConstraints": {},
      "isRLSEnabled": false
    },
    "public.recipe_allergen": {
      "name": "recipe_allergen",
      "schema": "",
      "columns": {
        "id": {
          "name": "id",
          "type": "uuid",
          "primaryKey": true,
          "notNull": true,
          "default": "gen_random_uuid()"
        },
        "recipe_id": {
          "name": "recipe_id",
          "type": "uuid",
          "primaryKey": false,
          "notNull": true
        },
        "allergen": {
          "name": "allergen",
          "type": "allergen",
          "typeSchema": "public",
          "primaryKey": false,
          "notNull": true
        },
        "contains": {
          "name": "contains",
          "type": "boolean",
          "primaryKey": false,
          "notNull": true,
          "default": false
        },
        "may_contain_traces": {
          "name": "may_contain_traces",
          "type": "boolean",
          "primaryKey": false,
          "notNull": true,
          "default": false
        },
        "human_confirmed": {
          "name": "human_confirmed",
          "type": "boolean",
          "primaryKey": false,
          "notNull": true,
          "default": false
        }
      },
      "indexes": {},
      "foreignKeys": {
        "recipe_allergen_recipe_id_recipe_id_fk": {
          "name": "recipe_allergen_recipe_id_recipe_id_fk",
          "tableFrom": "recipe_allergen",
          "tableTo": "recipe",
          "columnsFrom": [
            "recipe_id"
          ],
          "columnsTo": [
            "id"
          ],
          "onDelete": "cascade",
          "onUpdate": "no action"
        }
      },
      "compositePrimaryKeys": {},
      "uniqueConstraints": {},
      "policies": {},
      "checkConstraints": {},
      "isRLSEnabled": false
    },
    "public.recipe_ingredient": {
      "name": "recipe_ingredient",
      "schema": "",
      "columns": {
        "id": {
          "name": "id",
          "type": "uuid",
          "primaryKey": true,
          "notNull": true,
          "default": "gen_random_uuid()"
        },
        "recipe_id": {
          "name": "recipe_id",
          "type": "uuid",
          "primaryKey": false,
          "notNull": true
        },
        "ingredient_id": {
          "name": "ingredient_id",
          "type": "uuid",
          "primaryKey": false,
          "notNull": true
        },
        "quantity": {
          "name": "quantity",
          "type": "real",
          "primaryKey": false,
          "notNull": false
        },
        "unit": {
          "name": "unit",
          "type": "text",
          "primaryKey": false,
          "notNull": false
        }
      },
      "indexes": {},
      "foreignKeys": {
        "recipe_ingredient_recipe_id_recipe_id_fk": {
          "name": "recipe_ingredient_recipe_id_recipe_id_fk",
          "tableFrom": "recipe_ingredient",
          "tableTo": "recipe",
          "columnsFrom": [
            "recipe_id"
          ],
          "columnsTo": [
            "id"
          ],
          "onDelete": "cascade",
          "onUpdate": "no action"
        },
        "recipe_ingredient_ingredient_id_ingredient_id_fk": {
          "name": "recipe_ingredient_ingredient_id_ingredient_id_fk",
          "tableFrom": "recipe_ingredient",
          "tableTo": "ingredient",
          "columnsFrom": [
            "ingredient_id"
          ],
          "columnsTo": [
            "id"
          ],
          "onDelete": "no action",
          "onUpdate": "no action"
        }
      },
      "compositePrimaryKeys": {},
      "uniqueConstraints": {},
      "policies": {},
      "checkConstraints": {},
      "isRLSEnabled": false
    }
  },
  "enums": {
    "public.allergen": {
      "name": "allergen",
      "schema": "public",
      "values": [
        "gluten",
        "crustaceans",
        "egg",
        "fish",
        "peanut",
        "soy",
        "milk",
        "tree_nut",
        "celery",
        "mustard",
        "sesame",
        "sulphite",
        "lupin",
        "mollusc",
        "almond",
        "hazelnut",
        "walnut",
        "cashew",
        "pecan",
        "brazil_nut",
        "pistachio",
        "macadamia"
      ]
    },
    "public.effort_tier": {
      "name": "effort_tier",
      "schema": "public",
      "values": [
        "express",
        "standard",
        "relaxed"
      ]
    }
  },
  "schemas": {},
  "sequences": {},
  "roles": {},
  "policies": {},
  "views": {},
  "_meta": {
    "columns": {},
    "schemas": {},
    "tables": {}
  }
}